{
  "schema_version": 1,
  "seed": 1090,
  "number_placement": "official_spiral",
  "map_template": "BASE",
  "vps_to_win": 10,
  "board_fingerprint": "e155599253be",
  "robber_coordinate": [
    2,
    0,
    -2
  ],
  "tiles": [
    {
      "id": 0,
      "coordinate": [
        0,
        0,
        0
      ],
      "type": "RESOURCE_TILE",
      "resource": "BRICK",
      "number": 11
    },
    {
      "id": 1,
      "coordinate": [
        1,
        -1,
        0
      ],
      "type": "RESOURCE_TILE",
      "resource": "WOOD",
      "number": 10
    },
    {
      "id": 2,
      "coordinate": [
        0,
        -1,
        1
      ],
      "type": "RESOURCE_TILE",
      "resource": "WHEAT",
      "number": 3
    },
    {
      "id": 3,
      "coordinate": [
        -1,
        0,
        1
      ],
      "type": "RESOURCE_TILE",
      "resource": "BRICK",
      "number": 6
    },
    {
      "id": 4,
      "coordinate": [
        -1,
        1,
        0
      ],
      "type": "RESOURCE_TILE",
      "resource": "WHEAT",
      "number": 5
    },
    {
      "id": 5,
      "coordinate": [
        0,
        1,
        -1
      ],
      "type": "RESOURCE_TILE",
      "resource": "WOOD",
      "number": 4
    },
    {
      "id": 6,
      "coordinate": [
        1,
        0,
        -1
      ],
      "type": "RESOURCE_TILE",
      "resource": "SHEEP",
      "number": 9
    },
    {
      "id": 7,
      "coordinate": [
        2,
        -2,
        0
      ],
      "type": "RESOURCE_TILE",
      "resource": "WOOD",
      "number": 5
    },
    {
      "id": 8,
      "coordinate": [
        1,
        -2,
        1
      ],
      "type": "RESOURCE_TILE",
      "resource": "SHEEP",
      "number": 8
    },
    {
      "id": 9,
      "coordinate": [
        0,
        -2,
        2
      ],
      "type": "RESOURCE_TILE",
      "resource": "ORE",
      "number": 4
    },
    {
      "id": 10,
      "coordinate": [
        -1,
        -1,
        2
      ],
      "type": "RESOURCE_TILE",
      "resource": "BRICK",
      "number": 11
    },
    {
      "id": 11,
      "coordinate": [
        -2,
        0,
        2
      ],
      "type": "RESOURCE_TILE",
      "resource": "WHEAT",
      "number": 12
    },
    {
      "id": 12,
      "coordinate": [
        -2,
        1,
        1
      ],
      "type": "RESOURCE_TILE",
      "resource": "ORE",
      "number": 9
    },
    {
      "id": 13,
      "coordinate": [
        -2,
        2,
        0
      ],
      "type": "RESOURCE_TILE",
      "resource": "ORE",
      "number": 10
    },
    {
      "id": 14,
      "coordinate": [
        -1,
        2,
        -1
      ],
      "type": "RESOURCE_TILE",
      "resource": "SHEEP",
      "number": 8
    },
    {
      "id": 15,
      "coordinate": [
        0,
        2,
        -2
      ],
      "type": "RESOURCE_TILE",
      "resource": "WHEAT",
      "number": 3
    },
    {
      "id": 16,
      "coordinate": [
        1,
        1,
        -2
      ],
      "type": "RESOURCE_TILE",
      "resource": "WOOD",
      "number": 6
    },
    {
      "id": 17,
      "coordinate": [
        2,
        0,
        -2
      ],
      "type": "DESERT",
      "resource": null,
      "number": null
    },
    {
      "id": 18,
      "coordinate": [
        2,
        -1,
        -1
      ],
      "type": "RESOURCE_TILE",
      "resource": "SHEEP",
      "number": 2
    }
  ],
  "ports": [
    {
      "id": 0,
      "resource": "SHEEP",
      "direction": "WEST",
      "nodes": [
        25,
        26,
        54,
        55,
        56,
        57
      ]
    },
    {
      "id": 1,
      "resource": "WHEAT",
      "direction": "NORTHWEST",
      "nodes": [
        28,
        29,
        30,
        59,
        60,
        61
      ]
    },
    {
      "id": 2,
      "resource": null,
      "direction": "NORTHWEST",
      "nodes": [
        31,
        32,
        33,
        64,
        65,
        66
      ]
    },
    {
      "id": 3,
      "resource": "ORE",
      "direction": "NORTHEAST",
      "nodes": [
        35,
        36,
        68,
        69,
        70,
        71
      ]
    },
    {
      "id": 4,
      "resource": "WOOD",
      "direction": "EAST",
      "nodes": [
        38,
        39,
        41,
        73,
        74,
        75
      ]
    },
    {
      "id": 5,
      "resource": "BRICK",
      "direction": "EAST",
      "nodes": [
        40,
        42,
        44,
        76,
        79,
        80
      ]
    },
    {
      "id": 6,
      "resource": null,
      "direction": "SOUTHEAST",
      "nodes": [
        45,
        47,
        81,
        83,
        84,
        85
      ]
    },
    {
      "id": 7,
      "resource": null,
      "direction": "SOUTHWEST",
      "nodes": [
        48,
        49,
        50,
        87,
        88,
        89
      ]
    },
    {
      "id": 8,
      "resource": null,
      "direction": "SOUTHWEST",
      "nodes": [
        51,
        52,
        53,
        92,
        93,
        94
      ]
    }
  ],
  "board_id": "init_0090",
  "split": "example_pool"
}